numdiff/__about__.py
numdiff/__init__.py
numdiff/log.py
numdiff-0.0.2.dist-info/METADATA
numdiff-0.0.2.dist-info/WHEEL
numdiff-0.0.2.dist-info/dependency_links.txt
numdiff-0.0.2.dist-info/top_level.txt
numdiff-0.0.2.dist-info/RECORD
